{
  "10320/loc": "<locations><location href=\"https://dev.dissco.tech/ds/TEST/3MD-Q3C-T6M\" id=\"0\" weight=\"1\"/><location href=\"https://dev.dissco.tech/api/v1/specimens/TEST/3MD-Q3C-T6M\" id=\"1\" weight=\"0\"/></locations>",
  "fdoProfile": "https://hdl.handle.net/21.T11148/d8de0819e144e4096645",
  "fdoRecordLicense": "https://creativecommons.org/publicdomain/zero/1.0/",
  "digitalObjectType": "https://hdl.handle.net/21.T11148/d8de0819e144e4096645",
  "digitalObjectName": "Digital Specimen",
  "pid": "https://hdl.handle.net/TEST/3MD-Q3C-T6M",
  "pidIssuer": "https://ror.org/04wxnsj81",
  "pidIssuerName": "DataCite",
  "issuedForAgent": "https://ror.org/0566bfb96",
  "issuedForAgentName": "Naturalis Biodiversity Center",
  "pidRecordIssueDate": "2023-10-16T11:35:51.927Z",
  "pidRecordIssueNumber": 1,
  "structuralType": "digital",
  "pidStatus": "TEST",
  "referentType": "digitalSpecimen",
  "referentDoiName": "TEST/3MD-Q3C-T6M",
  "referentName": "Cyclocephala pugnax Arrow, 1914",
  "primaryReferentType": "creation",
  "specimenHost": "https://ror.org/03wkt5x30",
  "specimenHostName": "National Museum of Natural History",
  "primarySpecimenObjectId": "http://coldb.mnhn.fr/catalognumber/mnhn/ec/ec23797",
  "primarySpecimenObjectIdType": "Resolvable",
  "normalisedPrimarySpecimenObjectId": "http://coldb.mnhn.fr/catalognumber/mnhn/ec/ec23797",
  "topicDiscipline": "Botany",
  "livingOrPreserved": "Preserved"
}